galaxy_ml/__init__.py
galaxy_ml/feature_selectors.py
galaxy_ml/iraps_classifier.py
galaxy_ml/keras_galaxy_models.py
galaxy_ml/utils.py
galaxy_ml/binarize_target/__init__.py
galaxy_ml/binarize_target/_binarize_estimators.py
galaxy_ml/binarize_target/_iraps_classifier.py
galaxy_ml/binarize_target/_scorers.py
galaxy_ml/externals/__init__.py
galaxy_ml/externals/selene_sdk/__init__.py
galaxy_ml/externals/selene_sdk/predict/__init__.py
galaxy_ml/externals/selene_sdk/predict/_common.py
galaxy_ml/externals/selene_sdk/predict/_variant_effect_prediction.py
galaxy_ml/externals/selene_sdk/sequences/__init__.py
galaxy_ml/externals/selene_sdk/sequences/_sequence.c
galaxy_ml/externals/selene_sdk/sequences/_sequence.cpython-37m-darwin.so
galaxy_ml/externals/selene_sdk/sequences/_sequence.pyx
galaxy_ml/externals/selene_sdk/sequences/genome.py
galaxy_ml/externals/selene_sdk/sequences/proteome.py
galaxy_ml/externals/selene_sdk/sequences/sequence.py
galaxy_ml/externals/selene_sdk/sequences/data/hg19_blacklist_ENCFF001TDO.bed.gz
galaxy_ml/externals/selene_sdk/sequences/data/hg19_blacklist_ENCFF001TDO.bed.gz.tbi
galaxy_ml/externals/selene_sdk/sequences/data/hg38.blacklist.bed.gz
galaxy_ml/externals/selene_sdk/sequences/data/hg38.blacklist.bed.gz.tbi
galaxy_ml/externals/selene_sdk/targets/__init__.py
galaxy_ml/externals/selene_sdk/targets/_genomic_features.c
galaxy_ml/externals/selene_sdk/targets/_genomic_features.cpython-37m-darwin.so
galaxy_ml/externals/selene_sdk/targets/_genomic_features.pyx
galaxy_ml/externals/selene_sdk/targets/genomic_features.py
galaxy_ml/externals/selene_sdk/targets/target.py
galaxy_ml/externals/selene_sdk/utils/__init__.py
galaxy_ml/externals/selene_sdk/utils/performance_metrics.py
galaxy_ml/externals/selene_sdk/utils/utils.py
galaxy_ml/metrics/__init__.py
galaxy_ml/metrics/_regression.py
galaxy_ml/model_persist/__init__.py
galaxy_ml/model_persist/_pickle_hdf5.py
galaxy_ml/model_persist/_pickle_json.py
galaxy_ml/model_persist/_safe_pickler.py
Galaxy_ML-0.9.1.dist-info/LICENSE
Galaxy_ML-0.9.1.dist-info/METADATA
Galaxy_ML-0.9.1.dist-info/WHEEL
Galaxy_ML-0.9.1.dist-info/top_level.txt
Galaxy_ML-0.9.1.dist-info/RECORD
